<?xml version="1.0" encoding="UTF-8"?>
<lido:lidoWrap xmlns:lido="http://www.lido-schema.org" xmlns:gml="http://www.opengis.net/gml" xmlns:xsi="http://www.w3.org/2001/XMLSchema-instance" xmlns:xalan="http://xml.apache.org/xalan" xsi:schemaLocation="http://www.lido-schema.org http://www.lido-schema.org/schema/v1.0/lido-v1.0.xsd http://www.opengis.net/gml http://schemas.opengis.net/gml/3.1.1/base/feature.xsd">
  <lido:lido>
    <lido:lidoRecID lido:source="https://westfalen.museum-digital.de/institution/61" lido:type="local">DE-Bm56/24908</lido:lidoRecID>
    <lido:category/>
    <lido:descriptiveMetadata xml:lang="de">
      <lido:objectClassificationWrap>
        <lido:objectWorkTypeWrap>
          <lido:objectWorkType>
            <lido:conceptID lido:source="md:term" lido:type="uri">https://term.museum-digital.de/md-de/tag/130907</lido:conceptID>
            <lido:term xml:lang="de">Dia</lido:term>
          </lido:objectWorkType>
        </lido:objectWorkTypeWrap>
        <lido:classificationWrap>
          <lido:classification lido:type="Sammlung">
            <lido:conceptID lido:source="local" lido:type="collection_id">670</lido:conceptID>
            <lido:term xml:lang="de" lido:addedSearchTerm="no">Fotosammlung Stereofotografien</lido:term>
          </lido:classification>
        </lido:classificationWrap>
      </lido:objectClassificationWrap>
      <lido:objectIdentificationWrap>
        <lido:titleWrap>
          <lido:titleSet>
            <lido:appellationValue lido:pref="preferred">Erzverladung über Tage per Bahn, Schacht Emilie, Erzbergbau Bülten</lido:appellationValue>
          </lido:titleSet>
        </lido:titleWrap>
        <lido:repositoryWrap>
          <lido:repositorySet lido:type="current">
            <lido:repositoryName>
              <lido:legalBodyID lido:type="isil">DE-Bm56</lido:legalBodyID>
              <lido:legalBodyName>
                <lido:appellationValue>Deutsches Bergbau-Museum Bochum – Leibniz-Forschungsmuseum für Georessourcen</lido:appellationValue>
              </lido:legalBodyName>
              <lido:legalBodyWeblink>https://www.bergbaumuseum.de/</lido:legalBodyWeblink>
            </lido:repositoryName>
            <lido:workID lido:type="inventory number">120160167001</lido:workID>
            <lido:repositoryLocation>
              <lido:namePlaceSet>
                <lido:appellationValue>Bochum</lido:appellationValue>
              </lido:namePlaceSet>
              <lido:gml>
                <gml:Point srsName="EPSG:4326">
                  <gml:pos>51.48910522 7.21717024</gml:pos>
                </gml:Point>
              </lido:gml>
            </lido:repositoryLocation>
          </lido:repositorySet>
        </lido:repositoryWrap>
        <lido:objectDescriptionWrap>
          <lido:objectDescriptionSet>
            <lido:descriptiveNoteValue>Diesellokomotive mit angehängten Güterwaggons; im Hintergrund Verladestelle, Fördergerüst und andere Tagesanlagen</lido:descriptiveNoteValue>
            <lido:sourceDescriptiveNote>Deutsches Bergbau-Museum Bochum – Leibniz-Forschungsmuseum für Georessourcen</lido:sourceDescriptiveNote>
          </lido:objectDescriptionSet>
        </lido:objectDescriptionWrap>
        <lido:objectMeasurementsWrap>
          <lido:objectMeasurementsSet>
            <lido:displayObjectMeasurements>Höhe: 60 mm; Breite: 130 mm</lido:displayObjectMeasurements>
            <lido:objectMeasurements>
              <lido:measurementsSet>
                <lido:measurementType>width</lido:measurementType>
                <lido:measurementUnit>mm</lido:measurementUnit>
                <lido:measurementValue>130</lido:measurementValue>
              </lido:measurementsSet>
              <lido:measurementsSet>
                <lido:measurementType>height</lido:measurementType>
                <lido:measurementUnit>mm</lido:measurementUnit>
                <lido:measurementValue>60</lido:measurementValue>
              </lido:measurementsSet>
            </lido:objectMeasurements>
          </lido:objectMeasurementsSet>
        </lido:objectMeasurementsWrap>
      </lido:objectIdentificationWrap>
      <lido:eventWrap>
        <lido:eventSet>
          <lido:displayEvent>Hergestellt</lido:displayEvent>
          <lido:event>
            <lido:eventID lido:type="local">513295</lido:eventID>
            <lido:eventType>
              <lido:conceptID lido:type="uri">https://event-types.museum-digital.org/1</lido:conceptID>
              <lido:term lido:addedSearchTerm="no">Hergestellt</lido:term>
            </lido:eventType>
            <lido:eventName>
              <lido:appellationValue/>
            </lido:eventName>
            <lido:eventActor>
              <lido:displayActorInRole>Herbert Kasper (Fotograf)</lido:displayActorInRole>
              <lido:actorInRole>
                <lido:actor>
                  <lido:actorID lido:source="md:term" lido:type="uri">https://term.museum-digital.de/md-de/persinst/199544</lido:actorID>
                  <lido:nameActorSet>
                    <lido:appellationValue>Kasper, Herbert (Fotograf)</lido:appellationValue>
                    <lido:appellationValue xml:lang="de">Herbert Kasper (Fotograf)</lido:appellationValue>
                  </lido:nameActorSet>
                  <lido:vitalDatesActor>
                    <lido:earliestDate/>
                    <lido:latestDate/>
                  </lido:vitalDatesActor>
                </lido:actor>
              </lido:actorInRole>
            </lido:eventActor>
            <lido:eventDate>
              <lido:displayDate>1972</lido:displayDate>
              <lido:displayDate xml:lang="ar">1972</lido:displayDate>
              <lido:displayDate xml:lang="de">1972</lido:displayDate>
              <lido:displayDate xml:lang="en">1972</lido:displayDate>
              <lido:displayDate xml:lang="es">1972</lido:displayDate>
              <lido:displayDate xml:lang="fa">1972</lido:displayDate>
              <lido:displayDate xml:lang="fr">1972</lido:displayDate>
              <lido:displayDate xml:lang="hu">1972</lido:displayDate>
              <lido:displayDate xml:lang="id">1972</lido:displayDate>
              <lido:displayDate xml:lang="it">1972</lido:displayDate>
              <lido:displayDate xml:lang="ja">1972年</lido:displayDate>
              <lido:displayDate xml:lang="ka">1972</lido:displayDate>
              <lido:displayDate xml:lang="ko">1972년</lido:displayDate>
              <lido:displayDate xml:lang="pl">1972</lido:displayDate>
              <lido:displayDate xml:lang="pt">1972</lido:displayDate>
              <lido:displayDate xml:lang="ro">1972</lido:displayDate>
              <lido:displayDate xml:lang="ru">1972</lido:displayDate>
              <lido:displayDate xml:lang="ta">1972</lido:displayDate>
              <lido:displayDate xml:lang="tl">1972</lido:displayDate>
              <lido:displayDate xml:lang="tr">1972</lido:displayDate>
              <lido:displayDate xml:lang="uk">1972</lido:displayDate>
              <lido:displayDate xml:lang="zh">1972年</lido:displayDate>
              <lido:date>
                <lido:earliestDate>1972</lido:earliestDate>
                <lido:latestDate>1972</lido:latestDate>
              </lido:date>
            </lido:eventDate>
          </lido:event>
        </lido:eventSet>
        <lido:eventSet>
          <lido:event>
            <lido:eventType>
              <lido:conceptID lido:type="uri">http://terminology.lido-schema.org/lido00003</lido:conceptID>
              <lido:term>Event (non-specified)</lido:term>
            </lido:eventType>
            <lido:eventMaterialsTech>
              <lido:displayMaterialsTech>Glas * Stereofotografie</lido:displayMaterialsTech>
            </lido:eventMaterialsTech>
            <lido:eventMaterialsTech>
              <lido:materialsTech>
                <lido:termMaterialsTech lido:type="material">
                  <lido:term>Glas</lido:term>
                </lido:termMaterialsTech>
              </lido:materialsTech>
            </lido:eventMaterialsTech>
            <lido:eventMaterialsTech>
              <lido:materialsTech>
                <lido:termMaterialsTech lido:type="technique">
                  <lido:term>Stereofotografie</lido:term>
                </lido:termMaterialsTech>
              </lido:materialsTech>
            </lido:eventMaterialsTech>
          </lido:event>
        </lido:eventSet>
      </lido:eventWrap>
      <lido:objectRelationWrap>
        <lido:subjectWrap>
          <lido:subjectSet>
            <lido:subject>
              <lido:subjectPlace>
                <lido:displayPlace>Zeche Bülten-Adenstedt</lido:displayPlace>
                <lido:displayPlace xml:lang="de">Zeche Bülten-Adenstedt</lido:displayPlace>
                <lido:displayPlace xml:lang="en">Bülten-Adenstedt iron ore mine</lido:displayPlace>
                <lido:place>
                  <lido:placeID lido:source="wikidata" lido:type="uri">https://www.wikidata.org/wiki/Q1549881</lido:placeID>
                  <lido:placeID lido:source="md:term" lido:type="uri">https://term.museum-digital.de/md-de/place/82119</lido:placeID>
                  <lido:namePlaceSet>
                    <lido:appellationValue>Zeche Bülten-Adenstedt</lido:appellationValue>
                    <lido:appellationValue xml:lang="de">Zeche Bülten-Adenstedt</lido:appellationValue>
                    <lido:appellationValue xml:lang="en">Bülten-Adenstedt iron ore mine</lido:appellationValue>
                  </lido:namePlaceSet>
                  <lido:gml>
                    <gml:Point srsName="EPSG:4326">
                      <gml:pos>52.279201507568 10.209199905396</gml:pos>
                    </gml:Point>
                  </lido:gml>
                </lido:place>
              </lido:subjectPlace>
            </lido:subject>
          </lido:subjectSet>
          <lido:subjectSet>
            <lido:subject>
              <lido:subjectConcept>
                <lido:conceptID lido:source="aat" lido:type="uri">http://vocab.getty.edu/aat/300055244</lido:conceptID>
                <lido:conceptID lido:source="bnf" lido:type="uri">https://catalogue.bnf.fr/ark:/12148/cb13318486w</lido:conceptID>
                <lido:conceptID lido:source="gnd" lido:type="uri">https://d-nb.info/gnd/4062901-6</lido:conceptID>
                <lido:conceptID lido:source="lcsh" lido:type="uri">http://id.loc.gov/authorities/subjects/sh85137027</lido:conceptID>
                <lido:conceptID lido:source="ndl" lido:type="uri">https://id.ndl.go.jp/auth/ndlna/00566818</lido:conceptID>
                <lido:conceptID lido:source="wikidata" lido:type="uri">https://www.wikidata.org/wiki/Q7590</lido:conceptID>
                <lido:conceptID lido:source="Wikipedia" lido:type="uri">https://de.wikipedia.org/wiki/Verkehr</lido:conceptID>
                <lido:conceptID lido:source="md:term" lido:type="uri">https://term.museum-digital.de/md-de/tag/702</lido:conceptID>
                <lido:term lido:addedSearchTerm="no">Transport</lido:term>
                <lido:term lido:addedSearchTerm="no" xml:lang="ar">نقل</lido:term>
                <lido:term lido:addedSearchTerm="no" xml:lang="bn">পরিবহন</lido:term>
                <lido:term lido:addedSearchTerm="no" xml:lang="cs">Doprava</lido:term>
                <lido:term lido:addedSearchTerm="no" xml:lang="da">Transport</lido:term>
                <lido:term lido:addedSearchTerm="no" xml:lang="de">Transport</lido:term>
                <lido:term lido:addedSearchTerm="no" xml:lang="el">Μεταφορές</lido:term>
                <lido:term lido:addedSearchTerm="no" xml:lang="en">Transport</lido:term>
                <lido:term lido:addedSearchTerm="no" xml:lang="es">Transporte</lido:term>
                <lido:term lido:addedSearchTerm="no" xml:lang="fa">ترابری</lido:term>
                <lido:term lido:addedSearchTerm="no" xml:lang="fi">Liikenne</lido:term>
                <lido:term lido:addedSearchTerm="no" xml:lang="fr">Transport</lido:term>
                <lido:term lido:addedSearchTerm="no" xml:lang="he">תחבורה</lido:term>
                <lido:term lido:addedSearchTerm="no" xml:lang="hi">परिवहन</lido:term>
                <lido:term lido:addedSearchTerm="no" xml:lang="hu">szállítás</lido:term>
                <lido:term lido:addedSearchTerm="no" xml:lang="id">Transportasi</lido:term>
                <lido:term lido:addedSearchTerm="no" xml:lang="it">Trasporto</lido:term>
                <lido:term lido:addedSearchTerm="no" xml:lang="ja">交通</lido:term>
                <lido:term lido:addedSearchTerm="no" xml:lang="ka">ტრანსპორტი</lido:term>
                <lido:term lido:addedSearchTerm="no" xml:lang="ko">운송</lido:term>
                <lido:term lido:addedSearchTerm="no" xml:lang="nl">Vervoer</lido:term>
                <lido:term lido:addedSearchTerm="no" xml:lang="pl">Transport</lido:term>
                <lido:term lido:addedSearchTerm="no" xml:lang="pt">Transporte</lido:term>
                <lido:term lido:addedSearchTerm="no" xml:lang="ro">Transport</lido:term>
                <lido:term lido:addedSearchTerm="no" xml:lang="ru">транспорт</lido:term>
                <lido:term lido:addedSearchTerm="no" xml:lang="sv">Transport</lido:term>
                <lido:term lido:addedSearchTerm="no" xml:lang="sw">Usafiri</lido:term>
                <lido:term lido:addedSearchTerm="no" xml:lang="ta">போக்குவரத்து</lido:term>
                <lido:term lido:addedSearchTerm="no" xml:lang="th">การขนส่ง</lido:term>
                <lido:term lido:addedSearchTerm="no" xml:lang="tl">Transportasyon</lido:term>
                <lido:term lido:addedSearchTerm="no" xml:lang="tr">Ulaşım</lido:term>
                <lido:term lido:addedSearchTerm="no" xml:lang="uk">транспорт</lido:term>
                <lido:term lido:addedSearchTerm="no" xml:lang="ur">ٹرانسپورٹ</lido:term>
                <lido:term lido:addedSearchTerm="no" xml:lang="vi">vận tải</lido:term>
                <lido:term lido:addedSearchTerm="no" xml:lang="zh">运输</lido:term>
              </lido:subjectConcept>
            </lido:subject>
          </lido:subjectSet>
          <lido:subjectSet>
            <lido:subject>
              <lido:subjectConcept>
                <lido:conceptID lido:source="gnd" lido:type="uri">https://d-nb.info/gnd/4014015-5</lido:conceptID>
                <lido:conceptID lido:source="iconclass" lido:type="uri">http://iconclass.org/rkd/46C151</lido:conceptID>
                <lido:conceptID lido:source="lcsh" lido:type="uri">http://id.loc.gov/vocabulary/graphicMaterials/tgm008607</lido:conceptID>
                <lido:conceptID lido:source="wikidata" lido:type="uri">https://www.wikidata.org/wiki/Q22667</lido:conceptID>
                <lido:conceptID lido:source="Wikipedia" lido:type="uri">https://de.wikipedia.org/wiki/Eisenbahn</lido:conceptID>
                <lido:conceptID lido:source="md:term" lido:type="uri">https://term.museum-digital.de/md-de/tag/876</lido:conceptID>
                <lido:term lido:addedSearchTerm="no">Eisenbahn</lido:term>
                <lido:term lido:addedSearchTerm="no" xml:lang="ar">طريق/خط السكة الحديدية</lido:term>
                <lido:term lido:addedSearchTerm="no" xml:lang="cs">železnice</lido:term>
                <lido:term lido:addedSearchTerm="no" xml:lang="da">Jernbane</lido:term>
                <lido:term lido:addedSearchTerm="no" xml:lang="de">Eisenbahn</lido:term>
                <lido:term lido:addedSearchTerm="no" xml:lang="el">Σιδηρόδρομος</lido:term>
                <lido:term lido:addedSearchTerm="no" xml:lang="en">Railway</lido:term>
                <lido:term lido:addedSearchTerm="no" xml:lang="es">Ferrocarril</lido:term>
                <lido:term lido:addedSearchTerm="no" xml:lang="fa">راه‌آهن</lido:term>
                <lido:term lido:addedSearchTerm="no" xml:lang="fr">Chemin de fer</lido:term>
                <lido:term lido:addedSearchTerm="no" xml:lang="hi">रेल</lido:term>
                <lido:term lido:addedSearchTerm="no" xml:lang="hu">vasút</lido:term>
                <lido:term lido:addedSearchTerm="no" xml:lang="it">Ferrovia</lido:term>
                <lido:term lido:addedSearchTerm="no" xml:lang="ja">鉄道</lido:term>
                <lido:term lido:addedSearchTerm="no" xml:lang="ko">철도</lido:term>
                <lido:term lido:addedSearchTerm="no" xml:lang="nl">Spoorwegsysteem</lido:term>
                <lido:term lido:addedSearchTerm="no" xml:lang="pl">Kolej</lido:term>
                <lido:term lido:addedSearchTerm="no" xml:lang="pt">Ferrovia</lido:term>
                <lido:term lido:addedSearchTerm="no" xml:lang="ro">Cale ferată</lido:term>
                <lido:term lido:addedSearchTerm="no" xml:lang="ru">железная дорога</lido:term>
                <lido:term lido:addedSearchTerm="no" xml:lang="sv">Järnväg</lido:term>
                <lido:term lido:addedSearchTerm="no" xml:lang="sw">Reli</lido:term>
                <lido:term lido:addedSearchTerm="no" xml:lang="tr">Demiryolu</lido:term>
                <lido:term lido:addedSearchTerm="no" xml:lang="uk">залізниця</lido:term>
                <lido:term lido:addedSearchTerm="no" xml:lang="ur">پٹری</lido:term>
                <lido:term lido:addedSearchTerm="no" xml:lang="zh">鐵路系統</lido:term>
              </lido:subjectConcept>
            </lido:subject>
          </lido:subjectSet>
          <lido:subjectSet>
            <lido:subject>
              <lido:subjectConcept>
                <lido:conceptID lido:source="gnd" lido:type="uri">http://d-nb.info/gnd/4255904-2</lido:conceptID>
                <lido:conceptID lido:source="wikidata" lido:type="uri">https://www.wikidata.org/wiki/Q683835</lido:conceptID>
                <lido:conceptID lido:source="Wikipedia" lido:type="uri">https://de.wikipedia.org/wiki/F%C3%B6rderger%C3%BCst</lido:conceptID>
                <lido:conceptID lido:source="md:term" lido:type="uri">https://term.museum-digital.de/md-de/tag/28098</lido:conceptID>
                <lido:term lido:addedSearchTerm="no">Fördergerüst</lido:term>
                <lido:term lido:addedSearchTerm="no" xml:lang="cs">Těžní věž</lido:term>
                <lido:term lido:addedSearchTerm="no" xml:lang="de">Fördergerüst</lido:term>
                <lido:term lido:addedSearchTerm="no" xml:lang="en">Headframe</lido:term>
                <lido:term lido:addedSearchTerm="no" xml:lang="es">Castillete</lido:term>
                <lido:term lido:addedSearchTerm="no" xml:lang="fr">Chevalement</lido:term>
                <lido:term lido:addedSearchTerm="no" xml:lang="nl">Schachtbok</lido:term>
                <lido:term lido:addedSearchTerm="no" xml:lang="pl">Wieża szybowa</lido:term>
                <lido:term lido:addedSearchTerm="no" xml:lang="ru">копёр</lido:term>
                <lido:term lido:addedSearchTerm="no" xml:lang="sv">Lave</lido:term>
                <lido:term lido:addedSearchTerm="no" xml:lang="uk">копер</lido:term>
              </lido:subjectConcept>
            </lido:subject>
          </lido:subjectSet>
          <lido:subjectSet>
            <lido:subject>
              <lido:subjectConcept>
                <lido:conceptID lido:source="aat" lido:type="uri">http://vocab.getty.edu/aat/300212993</lido:conceptID>
                <lido:conceptID lido:source="gnd" lido:type="uri">https://d-nb.info/gnd/4022497-1</lido:conceptID>
                <lido:conceptID lido:source="wikidata" lido:type="uri">https://www.wikidata.org/wiki/Q9166501</lido:conceptID>
                <lido:conceptID lido:source="Wikipedia" lido:type="uri">https://de.wikipedia.org/wiki/G%C3%BCterwagen</lido:conceptID>
                <lido:conceptID lido:source="md:term" lido:type="uri">https://term.museum-digital.de/md-de/tag/53753</lido:conceptID>
                <lido:term lido:addedSearchTerm="no">Güterwagen</lido:term>
                <lido:term lido:addedSearchTerm="no" xml:lang="ar">عربة البضائع</lido:term>
                <lido:term lido:addedSearchTerm="no" xml:lang="cs">Nákladní vůz</lido:term>
                <lido:term lido:addedSearchTerm="no" xml:lang="da">Godsvogn</lido:term>
                <lido:term lido:addedSearchTerm="no" xml:lang="de">Güterwagen</lido:term>
                <lido:term lido:addedSearchTerm="no" xml:lang="en">Freight car</lido:term>
                <lido:term lido:addedSearchTerm="no" xml:lang="es">Vagón de ferrocarril</lido:term>
                <lido:term lido:addedSearchTerm="no" xml:lang="fi">Tavaravaunu</lido:term>
                <lido:term lido:addedSearchTerm="no" xml:lang="fr">Wagon</lido:term>
                <lido:term lido:addedSearchTerm="no" xml:lang="hu">teherkocsi</lido:term>
                <lido:term lido:addedSearchTerm="no" xml:lang="id">Gerbong</lido:term>
                <lido:term lido:addedSearchTerm="no" xml:lang="it">Carro merci</lido:term>
                <lido:term lido:addedSearchTerm="no" xml:lang="ja">貨車</lido:term>
                <lido:term lido:addedSearchTerm="no" xml:lang="ko">화차</lido:term>
                <lido:term lido:addedSearchTerm="no" xml:lang="nl">Goederenwagon</lido:term>
                <lido:term lido:addedSearchTerm="no" xml:lang="pl">Wagon towarowy</lido:term>
                <lido:term lido:addedSearchTerm="no" xml:lang="pt">Vagão</lido:term>
                <lido:term lido:addedSearchTerm="no" xml:lang="ru">грузовой вагон</lido:term>
                <lido:term lido:addedSearchTerm="no" xml:lang="sv">Godsvagn</lido:term>
                <lido:term lido:addedSearchTerm="no" xml:lang="uk">вантажний вагон</lido:term>
                <lido:term lido:addedSearchTerm="no" xml:lang="zh">鐵路貨車</lido:term>
              </lido:subjectConcept>
            </lido:subject>
          </lido:subjectSet>
          <lido:subjectSet>
            <lido:subject>
              <lido:subjectConcept>
                <lido:conceptID lido:source="md:term" lido:type="uri">https://term.museum-digital.de/md-de/tag/100289</lido:conceptID>
                <lido:term lido:addedSearchTerm="no">Tagesanlagen</lido:term>
              </lido:subjectConcept>
            </lido:subject>
          </lido:subjectSet>
        </lido:subjectWrap>
        <lido:relatedWorksWrap>
          <lido:relatedWorkSet>
            <lido:relatedWork>
              <lido:displayObject>Objekt in der Datenbank des montan.dok</lido:displayObject>
              <lido:object>
                <lido:objectWebResource>https://www.montandok.de/objekt_start.fau?prj=montandok&amp;dm=Montanhistorisches+Dokumentationszentrum&amp;ref=291941</lido:objectWebResource>
              </lido:object>
            </lido:relatedWork>
          </lido:relatedWorkSet>
        </lido:relatedWorksWrap>
      </lido:objectRelationWrap>
    </lido:descriptiveMetadata>
    <lido:administrativeMetadata xml:lang="de">
      <lido:rightsWorkWrap>
        <lido:rightsWorkSet>
          <lido:rightsHolder>
            <lido:legalBodyName>
              <lido:appellationValue>Deutsches Bergbau-Museum Bochum – Leibniz-Forschungsmuseum für Georessourcen</lido:appellationValue>
            </lido:legalBodyName>
          </lido:rightsHolder>
        </lido:rightsWorkSet>
      </lido:rightsWorkWrap>
      <lido:recordWrap>
        <lido:recordID lido:type="museum-digital">24908</lido:recordID>
        <lido:recordType>
          <lido:term lido:addedSearchTerm="no">item</lido:term>
        </lido:recordType>
        <lido:recordSource lido:type="dataProvider">
          <lido:legalBodyName>
            <lido:appellationValue>museum-digital</lido:appellationValue>
          </lido:legalBodyName>
          <lido:legalBodyWeblink>https://westfalen.museum-digital.de/</lido:legalBodyWeblink>
        </lido:recordSource>
        <lido:recordSource>
          <lido:legalBodyID lido:type="isil">DE-Bm56</lido:legalBodyID>
          <lido:legalBodyName>
            <lido:appellationValue>Deutsches Bergbau-Museum Bochum – Leibniz-Forschungsmuseum für Georessourcen</lido:appellationValue>
          </lido:legalBodyName>
        </lido:recordSource>
        <lido:recordRights>
          <lido:rightsType>
            <lido:conceptID lido:type="uri">https://creativecommons.org/publicdomain/zero/1.0/</lido:conceptID>
            <lido:term lido:addedSearchTerm="no">CC 0</lido:term>
          </lido:rightsType>
          <lido:rightsHolder>
            <lido:legalBodyName>
              <lido:appellationValue>Montanhistorisches Dokumentationszentrum (montan.dok)</lido:appellationValue>
            </lido:legalBodyName>
          </lido:rightsHolder>
          <lido:creditLine>Die Digitalisierung wurde durch die Deutsche Digitale Bibliothek im Rahmen des von der Beauftragten der Bundesregierung für Kultur und Medien (BKM) geförderten Programms NEUSTART KULTUR ermöglicht.</lido:creditLine>
        </lido:recordRights>
        <lido:recordInfoSet>
          <lido:recordInfoLink>https://westfalen.museum-digital.de/object/24908</lido:recordInfoLink>
          <lido:recordMetadataDate>2024-06-29 16:49:38</lido:recordMetadataDate>
        </lido:recordInfoSet>
      </lido:recordWrap>
      <lido:resourceWrap>
        <lido:resourceSet lido:sortorder="1">
          <lido:resourceID lido:source="resource" lido:type="local">32271</lido:resourceID>
          <lido:resourceRepresentation lido:type="image_thumb">
            <lido:linkResource lido:formatResource="image/jpeg">https://westfalen.museum-digital.de/data/westfalen/resources/documents/202208/100h_62e931014083a.jpg</lido:linkResource>
          </lido:resourceRepresentation>
          <lido:resourceRepresentation lido:type="image_preview">
            <lido:linkResource lido:formatResource="image/jpeg">https://westfalen.museum-digital.de/data/westfalen/resources/documents/202208/200w_62e931014083a.jpg</lido:linkResource>
          </lido:resourceRepresentation>
          <lido:resourceRepresentation lido:type="image_master">
            <lido:linkResource lido:formatResource="image/jpeg">https://www.montandok.de/bild_start.fau?prj=montandok&amp;dm=Montanhistorisches+Dokumentationszentrum&amp;zeig=291941&amp;rpos=1</lido:linkResource>
          </lido:resourceRepresentation>
          <lido:resourceType>
            <lido:term>image</lido:term>
          </lido:resourceType>
          <lido:resourceRelType>
            <lido:term>Hauptansicht</lido:term>
          </lido:resourceRelType>
          <lido:resourceDescription>Erzverladung über Tage per Bahn, Schacht Emilie, Erzbergbau Bülten</lido:resourceDescription>
          <lido:resourceSource lido:type="owner">
            <lido:legalBodyName>
              <lido:appellationValue>Deutsches Bergbau-Museum Bochum, Montanhistorisches Dokumentationszentrum</lido:appellationValue>
            </lido:legalBodyName>
          </lido:resourceSource>
          <lido:resourceSource lido:type="creator">
            <lido:legalBodyName>
              <lido:appellationValue>Deutsches Bergbau-Museum Bochum, Montanhistorisches Dokumentationszentrum</lido:appellationValue>
            </lido:legalBodyName>
          </lido:resourceSource>
          <lido:rightsResource>
            <lido:rightsType>
              <lido:conceptID lido:type="uri">https://creativecommons.org/licenses/by-nc-sa/4.0/</lido:conceptID>
              <lido:term>CC BY-NC-SA</lido:term>
            </lido:rightsType>
            <lido:rightsHolder>
              <lido:legalBodyName>
                <lido:appellationValue>Deutsches Bergbau-Museum Bochum, Montanhistorisches Dokumentationszentrum</lido:appellationValue>
              </lido:legalBodyName>
            </lido:rightsHolder>
            <lido:creditLine>Deutsches Bergbau-Museum Bochum, Montanhistorisches Dokumentationszentrum</lido:creditLine>
          </lido:rightsResource>
        </lido:resourceSet>
      </lido:resourceWrap>
    </lido:administrativeMetadata>
  </lido:lido>
</lido:lidoWrap>
